{
  "company": {
    "name": "Kalki Technologies",
    "brand": "Kalki Intelligency (KI)",
    "domain": "kalkicore.com",
    "tagline": "Open‑source intelligence engine for businesses",
    "mission": "Democratise AI by making it accessible, affordable, and completely private. No data leaves your device.",
    "vision": "Build the world's first distributed intelligence network – every user becomes a node, more users = smarter answers.",
    "founded": "2024",
    "legal": "Registered MSME (Udyam)",
    "core_values": ["Privacy First", "Open Source", "Community Driven", "Guaranteed ROI"]
  },
  "ai_assistant": {
    "name": "KI (Kalki Intelligency)",
    "personality": "Helpful, concise, enthusiastic about privacy, proud of being open‑source. Uses markdown formatting.",
    "capabilities": "Answers questions about digital marketing, web development, AI automation, SEO, social media, pricing, and company info.",
    "privacy_promise": "Your conversations never leave your browser – no servers, no logs, no tracking."
  },
  "services": {
    "static_website": {
      "price": "₹7,999 (one‑time)",
      "pages": "up to 5",
      "features": ["Responsive design", "SEO structure", "Contact form", "1 month free support"]
    },
    "dynamic_website": {
      "price": "₹12,999 (one‑time)",
      "pages": "up to 15 (Next.js)",
      "features": ["Admin dashboard", "Database integration", "Free 3 months hosting", "All static features"]
    },
    "gmb_seo": {
      "price": "₹8,999/month",
      "description": "Google Business Profile optimisation",
      "features": ["Google Maps #1 ranking", "Review management", "Local citations", "Monthly reports"]
    },
    "social_media": {
      "price": "₹9,999/month",
      "platforms": "Facebook + Instagram",
      "guarantee": "2 viral posts per month",
      "bonus": "Free blue tick verification",
      "features": ["Daily automation", "Engagement boosting"]
    },
    "seo_dominant": {
      "price": "₹9,999/month",
      "type": "Programmatic + On/Off Page",
      "features": ["50+ keywords ranking", "Programmatic SEO at scale", "Technical audit", "Monthly backlinks"]
    },
    "linkedin": {
      "price": "₹9,999/month",
      "bonus": "Free LinkedIn Premium",
      "features": ["Profile optimisation", "Lead generation campaigns", "Content strategy"]
    }
  },
  "ki_cloud": {
    "description": "Private AI that runs entirely in your browser using WebLLM",
    "model": "SmolLM2‑135M (tiny, fast, private)",
    "advantages": [
      "Zero data centre – your conversations never leave your device",
      "No account needed",
      "100% open source",
      "Distributed network – every visitor becomes a node"
    ]
  },
  "contact": {
    "whatsapp": "+91 6261031710",
    "email": "hello@kalki.tech",
    "response_time": "Within 24 hours"
  },
  "guarantee": "If you don't see measurable ROI within 90 days, we work for free until you do."
}
